setup.py
validity/__init__.py
validity/comparator.py
validity/logical_operator.py
validity.egg-info/PKG-INFO
validity.egg-info/SOURCES.txt
validity.egg-info/dependency_links.txt
validity.egg-info/not-zip-safe
validity.egg-info/top_level.txt