Metadata-Version: 1.0
Name: validity
Version: 0.1.0
Summary: validation tools
Home-page: https://github.com/Ivanukh/validity
Author: Yaroslav Ivanukh
Author-email: Ya.Ivanukh@gmail.com
License: GPL
Platform: UNKNOWN
